geo_ng/__init__.py
geo_ng/data/lgas.json
geo_ng/data/states.json
geo_ng/data/towns.json
geo_ng/geo_ng.py
geo_ng-1.0.0.dist-info/LICENSE
geo_ng-1.0.0.dist-info/METADATA
geo_ng-1.0.0.dist-info/WHEEL
geo_ng-1.0.0.dist-info/RECORD
