Metadata-Version: 2.1
Name: geo-ng
Version: 1.0.0
Summary: A python package that provides geographical information about States, Local Govenment Areas and towns in Nigeria
Author: ize-302
Author-email: adavizeozorku@gmail.com
Requires-Python: >=3.8,<4.0
Classifier: Programming Language :: Python :: 3
Classifier: Programming Language :: Python :: 3.8
Classifier: Programming Language :: Python :: 3.9
Classifier: Programming Language :: Python :: 3.10
Classifier: Programming Language :: Python :: 3.11
Classifier: Programming Language :: Python :: 3.12
Requires-Dist: setuptools (>=69.0.3,<70.0.0)
